iMail/__init__.py
iMail/iMail.py
iMail/utils.py
iMail-1.1.0.dist-info/LICENSE
iMail-1.1.0.dist-info/METADATA
iMail-1.1.0.dist-info/WHEEL
iMail-1.1.0.dist-info/top_level.txt
iMail-1.1.0.dist-info/RECORD
