Metadata-Version: 2.1
Name: iMail
Version: 1.1.0
Summary: A simple and effective email notification script.
Home-page: https://github.com/mtics/iMail
Author: Zhiwei Li
Author-email: lizhw.cs@outlook.com
License: MIT License
Platform: all
Classifier: Intended Audience :: Developers
Classifier: Operating System :: OS Independent
Classifier: License :: OSI Approved :: MIT License
Classifier: Natural Language :: English
Classifier: Programming Language :: Python :: 3
Classifier: Topic :: Communications :: Email
License-File: LICENSE
Requires-Dist: Pillow
